fhirclient/__init__.py
fhirclient/auth.py
fhirclient/client.py
fhirclient/embedded_schema_tests.py
fhirclient/fhirreference_tests.py
fhirclient/server.py
fhirclient/server_tests.py
fhirclient/simplify_tests.py
fhirclient/models/__init__.py
fhirclient/models/account.py
fhirclient/models/account_tests.py
fhirclient/models/activitydefinition.py
fhirclient/models/activitydefinition_tests.py
fhirclient/models/address.py
fhirclient/models/adverseevent.py
fhirclient/models/adverseevent_tests.py
fhirclient/models/age.py
fhirclient/models/allergyintolerance.py
fhirclient/models/allergyintolerance_tests.py
fhirclient/models/annotation.py
fhirclient/models/appointment.py
fhirclient/models/appointment_tests.py
fhirclient/models/appointmentresponse.py
fhirclient/models/appointmentresponse_tests.py
fhirclient/models/attachment.py
fhirclient/models/auditevent.py
fhirclient/models/auditevent_tests.py
fhirclient/models/backboneelement.py
fhirclient/models/basic.py
fhirclient/models/basic_tests.py
fhirclient/models/binary.py
fhirclient/models/binary_tests.py
fhirclient/models/biologicallyderivedproduct.py
fhirclient/models/biologicallyderivedproduct_tests.py
fhirclient/models/bodystructure.py
fhirclient/models/bodystructure_tests.py
fhirclient/models/bundle.py
fhirclient/models/bundle_tests.py
fhirclient/models/capabilitystatement.py
fhirclient/models/capabilitystatement_tests.py
fhirclient/models/careplan.py
fhirclient/models/careplan_tests.py
fhirclient/models/careteam.py
fhirclient/models/careteam_tests.py
fhirclient/models/catalogentry.py
fhirclient/models/catalogentry_tests.py
fhirclient/models/chargeitem.py
fhirclient/models/chargeitem_tests.py
fhirclient/models/chargeitemdefinition.py
fhirclient/models/chargeitemdefinition_tests.py
fhirclient/models/claim.py
fhirclient/models/claim_tests.py
fhirclient/models/claimresponse.py
fhirclient/models/claimresponse_tests.py
fhirclient/models/clinicalimpression.py
fhirclient/models/clinicalimpression_tests.py
fhirclientr4e-4.0.8.dist-info/AUTHORS.md
fhirclientr4e-4.0.8.dist-info/LICENSE
fhirclientr4e-4.0.8.dist-info/METADATA
fhirclientr4e-4.0.8.dist-info/WHEEL
fhirclientr4e-4.0.8.dist-info/top_level.txt
fhirclientr4e-4.0.8.dist-info/RECORD
